triangle_sector_similarity/__init__.py
triangle_sector_similarity-1.6.dist-info/LICENSE
triangle_sector_similarity-1.6.dist-info/METADATA
triangle_sector_similarity-1.6.dist-info/WHEEL
triangle_sector_similarity-1.6.dist-info/top_level.txt
triangle_sector_similarity-1.6.dist-info/RECORD
