Metadata-Version: 2.1
Name: triangle-sector-similarity
Version: 1.6
Summary: Find the similarity between vectors
Home-page: https://github.com/mohvam98/triangle_sector_similarity
Author: mohan98
Author-email: mohanavamsi98@gmail.com
License: MIT
Platform: UNKNOWN
Classifier: License :: OSI Approved :: MIT License
Classifier: Programming Language :: Python :: 3.6
Classifier: Programming Language :: Python :: 3.7
Classifier: Programming Language :: Python :: 3.8
Classifier: Programming Language :: Python :: 3.9
License-File: LICENSE
Requires-Dist: numpy
Requires-Dist: scipy
